edc_clinic/__init__.py
edc_clinic/apps.py
edc_clinic/choices.py
edc_clinic/constants.py
edc_clinic/migrations/__init__.py
edc_clinic/models/__init__.py
edc_clinic/models/creatinine_fields_model_mixin.py
edc_clinic/models/fasting_glucose_model_mixin.py
edc_clinic/models/fasting_model_mixin.py
edc_clinic/models/glucose_model_mixin.py
edc_clinic/models/medication_adherence_model_mixin.py
edc_clinic/models/ogtt_model_mixin.py
edc_clinic/tests/__init__.py
edc_clinic/tests/models.py
edc_clinic/tests/urls.py
edc_clinic/tests/tests/__init__.py
edc_clinic/tests/tests/test_glucose.py
edc_clinic-0.3.1.dist-info/LICENSE
edc_clinic-0.3.1.dist-info/METADATA
edc_clinic-0.3.1.dist-info/WHEEL
edc_clinic-0.3.1.dist-info/top_level.txt
edc_clinic-0.3.1.dist-info/RECORD
